datarec/__init__.py
datarec/data.py
datarec/tables/__init__.py
datarec/tables/_is_close_numeric.py
datarec/tables/_is_equal.py
datarec/tables/_method_base.py
datarec/tables/_reconciler.py
datarec/tables/_summarizer.py
datarec/utils/__init__.py
datarec/utils/_get_suffixed.py
datarec/utils/_set_case.py
datarec/utils/functions.py
datarec-0.3.1.dist-info/METADATA
datarec-0.3.1.dist-info/WHEEL
datarec-0.3.1.dist-info/license
datarec-0.3.1.dist-info/top_level.txt
datarec-0.3.1.dist-info/RECORD
