Metadata-Version: 2.1
Name: datarec
Version: 0.3.1
Summary: utilities for reconciling data
Author-email: Chris Mamon <chrisam1993@live.com>
Classifier: License :: OSI Approved :: MIT License
Classifier: Programming Language :: Python
Classifier: Programming Language :: Python :: 3.7
Classifier: Programming Language :: Python :: 3.8
Classifier: Programming Language :: Python :: 3.9
Classifier: Programming Language :: Python :: 3.10
Classifier: Programming Language :: Python :: 3.11
License-File: license
Requires-Dist: polars
